bup/__init__.py
bup/__main__.py
bup/__version__.py
bup/arguments.py
bup/backup_types.py
bup/bup.ico
bup/bup.png
bup/bup_base.py
bup/dynamodb_backup.py
bup/github_backup.py
bup/preferences.py
bup/print_log.py
bup/robust_os_calls.py
bup/s3_backup.py
bup/ui_types.py
bup/cli/__init__.py
bup/cli/cli_main.py
bup/gui/__init__.py
bup/gui/about.py
bup/gui/bup_dialog.py
bup/gui/gui_icon.py
bup/gui/gui_main.py
bup/gui/preferences_widget.py
bup/gui/run_backup_widget.py
bup-0.4.3.data/data/LICENSE
bup-0.4.3.data/data/LICENSE.txt
bup-0.4.3.data/data/gpl-3.0.md
bup-0.4.3.data/data/readme.md
test_bup/__init__.py
test_bup/conftest.py
test_bup/test_preferences.py
test_bup/test_preferences_gui.py
test_bup/test_print_log.py
bup-0.4.3.dist-info/LICENSE
bup-0.4.3.dist-info/LICENSE.txt
bup-0.4.3.dist-info/METADATA
bup-0.4.3.dist-info/WHEEL
bup-0.4.3.dist-info/top_level.txt
bup-0.4.3.dist-info/RECORD
