Metadata-Version: 2.1
Name: bup
Version: 0.4.3
Summary: Backup utility
Home-page: https://github.com/jamesabel/bup
Download-URL: https://github.com/jamesabel/bup
Author: abel
Author-email: j@abel.co
License: GPL v3
Keywords: aws,dynamodb,s3,github,backup
License-File: LICENSE
License-File: LICENSE.txt
Requires-Dist: ismain
Requires-Dist: balsa
Requires-Dist: boto3
Requires-Dist: typeguard
Requires-Dist: hashy
Requires-Dist: dictim
Requires-Dist: awsimple
Requires-Dist: pressenter2exit
Requires-Dist: awscli
Requires-Dist: GitPython
Requires-Dist: github3.py
Requires-Dist: sqlitedict
Requires-Dist: tobool
Requires-Dist: attrs
Requires-Dist: appdirs
Requires-Dist: pref
Requires-Dist: pyqt5
